shortcm_client/__init__.py
shortcm_client/__main__.py
shortcm_client/bitly_import.py
shortcm_client/cmd.py
shortcm_client/csv_import.py
shortcm_client-0.5.dist-info/METADATA
shortcm_client-0.5.dist-info/RECORD
shortcm_client-0.5.dist-info/WHEEL
shortcm_client-0.5.dist-info/entry_points.txt
shortcm_client-0.5.dist-info/top_level.txt
